LICENSE
MANIFEST.in
README.md
setup.cfg
setup.py
docs/logo.png
docs/logo.svg
docs/source/Makefile
docs/source/conf.py
docs/source/faq.rst
docs/source/getting_started.rst
docs/source/index.rst
docs/source/installation.rst
docs/source/logo_flipped.png
docs/source/logo_restored.png
docs/source/api/ecvl.rst
docs/source/api/index.rst
examples/augmentations.py
examples/dataset.py
examples/dataset_generator.py
examples/ecvl_eddl.py
examples/img_format.py
examples/imgproc.py
examples/moments.py
examples/openslide.py
examples/pipeline.py
examples/read_write.py
examples/run_all.sh
pyecvl/__init__.py
pyecvl/arithmetic.py
pyecvl/augmentations.py
pyecvl/dataset_generator.py
pyecvl/dataset_parser.py
pyecvl/datatype.py
pyecvl/ecvl.py
pyecvl/image.py
pyecvl/imgproc.py
pyecvl/metadata.py
pyecvl/support_dcmtk.py
pyecvl/support_eddl.py
pyecvl/support_imgcodecs.py
pyecvl/support_nifti.py
pyecvl/support_openslide.py
pyecvl/version.py
pyecvl.egg-info/PKG-INFO
pyecvl.egg-info/SOURCES.txt
pyecvl.egg-info/dependency_links.txt
pyecvl.egg-info/not-zip-safe
pyecvl.egg-info/requires.txt
pyecvl.egg-info/top_level.txt
src/_core.cpp
src/dataset_addons.hpp
src/func_binder.hpp
src/generateclassificationdataset_addons.hpp
src/generatesegmentationdataset_addons.hpp
src/image_addons.hpp
src/image_ext.hpp
src/metadata_addons.hpp
src/sample_addons.hpp
src/split_addons.hpp
src/view_float32_addons.hpp
src/view_int16_addons.hpp
src/view_int8_addons.hpp
src/view_uint8_addons.hpp
tests/test_arithmetic.py
tests/test_augmentations.py
tests/test_dataset.py
tests/test_datatype.py
tests/test_eddl.py
tests/test_image.py
tests/test_imgproc.py
tests/test_metadata.py