Metadata-Version: 1.1
Name: pyecvl
Version: 1.2.0
Summary: Python wrapper for ECVL
Home-page: https://github.com/deephealthproject/pyecvl
Author: Simone Leo
Author-email: <simone.leo@crs4.it>
License: MIT
Platform: Linux
Classifier: Programming Language :: Python :: 3.6
Classifier: License :: OSI Approved :: MIT License
Classifier: Operating System :: POSIX :: Linux
Classifier: Topic :: Scientific/Engineering
Classifier: Intended Audience :: Science/Research
